{
  "imports": {
    "std/": "https://deno.land/std@0.106.0/",
    "x/": "https://deno.land/x/",
    "y/": "https://cdn.skypack.dev/",
    "@itsudeno": "./mod.ts",
    "@errors": "./core/errors/mod.ts",
    "@types": "./core/internal/types/mod.ts",
    "@settings": "./core/setup/settings.ts",
    "@generated/":"./core/generated/",
    "@testing": "./core/internal/testing/mod.ts",
    "@executors": "./core/generated/executors/mod.ts",
    "@executors/": "./executors/",
    "@interfaces/": "./interfaces/",
    "@interfaces/cli": "./interfaces/cli/mod.ts",
    "@inventories": "./core/generated/inventories/mod.ts",
    "@inventories/": "./inventories/",
    "@modules": "./core/generated/modules/mod.ts",
    "@modules/": "./modules/",
    "@reporters": "./core/generated/reporters/mod.ts",
    "@reporters/": "./reporters/",
    "@vaults":"./core/generated/vaults/mod.ts",
    "@vaults/":"./vaults/",
    "@core/": "./core/",
    "@core/executors": "./core/executors/mod.ts",
    "@core/inventories": "./core/inventories/mod.ts",
    "@core/modules": "./core/modules/mod.ts",
    "@core/reporters": "./core/reporters/mod.ts",
    "@core/setup": "./core/setup/mod.ts",
    "@core/setup/os": "./core/setup/os.ts",
    "@core/tasks": "./core/tasks/mod.ts",
    "@core/vaults": "./core/vaults/mod.ts",
    "@core/internal/common":"./core/internal/common/mod.ts",
    "@tools/internal":"./core/tools/internal.ts",
    "@tools/strings":"./core/tools/strings.ts",
    "@tools/hash":"./core/tools/hash.ts",
    "@tools/objects":"./core/tools/objects.ts",
    "@tools/is":"./core/tools/is.ts",
    "@tools/to":"./core/tools/to.ts",
    "@tools/flow":"./core/tools/flow.ts",
    "@tools/std":"./core/tools/std.ts",
    "@tools/run":"./core/tools/run.ts",
    "@tools/template":"./core/tools/template.ts",
    "@tools/log":"./core/tools/log.ts",
    "@tools/validate":"./core/tools/validate.ts"
  }
}
